// class version 50.0 (50)
// access flags 0x401
public abstract class TFluidHandler$$7$class {


  // access flags 0x9
  public static $init$(LTFluidHandler$$7;)V
    RETURN
    MAXSTACK = 1
    MAXLOCALS = 1

  // access flags 0x9
  public static bindPart(LTFluidHandler$$7;Lcodechicken/multipart/TMultiPart;)V
    ALOAD 0
    ALOAD 1
    INVOKEINTERFACE TFluidHandler$$7.TFluidHandler$$7$$super$bindPart (Lcodechicken/multipart/TMultiPart;)V
    ALOAD 1
    INSTANCEOF net/minecraftforge/fluids/IFluidHandler
    IFEQ L0
    ALOAD 0
    ALOAD 1
    CHECKCAST net/minecraftforge/fluids/IFluidHandler
    INVOKEINTERFACE TFluidHandler$$7.TFluidHandler$$7$$impl_$eq (Lnet/minecraftforge/fluids/IFluidHandler;)V
   L0
   FRAME FULL [TFluidHandler$$7 codechicken/multipart/TMultiPart] []
    RETURN
    MAXSTACK = 2
    MAXLOCALS = 2

  // access flags 0x9
  public static partRemoved(LTFluidHandler$$7;Lcodechicken/multipart/TMultiPart;I)V
    ALOAD 0
    ALOAD 1
    ILOAD 2
    INVOKEINTERFACE TFluidHandler$$7.TFluidHandler$$7$$super$partRemoved (Lcodechicken/multipart/TMultiPart;I)V
    ALOAD 1
    ALOAD 0
    INVOKEINTERFACE TFluidHandler$$7.TFluidHandler$$7$$impl ()Lnet/minecraftforge/fluids/IFluidHandler;
    IF_ACMPNE L0
    ALOAD 0
    ACONST_NULL
    INVOKEINTERFACE TFluidHandler$$7.TFluidHandler$$7$$impl_$eq (Lnet/minecraftforge/fluids/IFluidHandler;)V
   L0
   FRAME FULL [TFluidHandler$$7 codechicken/multipart/TMultiPart I] []
    RETURN
    MAXSTACK = 3
    MAXLOCALS = 3

  // access flags 0x9
  public static canAddPart(LTFluidHandler$$7;Lcodechicken/multipart/TMultiPart;)Z
    ALOAD 0
    INVOKEINTERFACE TFluidHandler$$7.TFluidHandler$$7$$impl ()Lnet/minecraftforge/fluids/IFluidHandler;
    IFNULL L0
    ALOAD 1
    INSTANCEOF net/minecraftforge/fluids/IFluidHandler
    IFEQ L0
    ICONST_0
    IRETURN
   L0
   FRAME FULL [TFluidHandler$$7 codechicken/multipart/TMultiPart] []
    ALOAD 0
    ALOAD 1
    INVOKEINTERFACE TFluidHandler$$7.TFluidHandler$$7$$super$canAddPart (Lcodechicken/multipart/TMultiPart;)Z
    IRETURN
    MAXSTACK = 2
    MAXLOCALS = 2

  // access flags 0x9
  public static getTankInfo(LTFluidHandler$$7;Lnet/minecraftforge/common/util/ForgeDirection;)[Lnet/minecraftforge/fluids/FluidTankInfo;
    ALOAD 0
    INVOKEINTERFACE TFluidHandler$$7.TFluidHandler$$7$$impl ()Lnet/minecraftforge/fluids/IFluidHandler;
    ALOAD 1
    INVOKEINTERFACE net/minecraftforge/fluids/IFluidHandler.getTankInfo (Lnet/minecraftforge/common/util/ForgeDirection;)[Lnet/minecraftforge/fluids/FluidTankInfo;
    ARETURN
    MAXSTACK = 2
    MAXLOCALS = 2

  // access flags 0x9
  public static drain(LTFluidHandler$$7;Lnet/minecraftforge/common/util/ForgeDirection;Lnet/minecraftforge/fluids/FluidStack;Z)Lnet/minecraftforge/fluids/FluidStack;
    ALOAD 0
    INVOKEINTERFACE TFluidHandler$$7.TFluidHandler$$7$$impl ()Lnet/minecraftforge/fluids/IFluidHandler;
    ALOAD 1
    ALOAD 2
    ILOAD 3
    INVOKEINTERFACE net/minecraftforge/fluids/IFluidHandler.drain (Lnet/minecraftforge/common/util/ForgeDirection;Lnet/minecraftforge/fluids/FluidStack;Z)Lnet/minecraftforge/fluids/FluidStack;
    ARETURN
    MAXSTACK = 4
    MAXLOCALS = 4

  // access flags 0x9
  public static fill(LTFluidHandler$$7;Lnet/minecraftforge/common/util/ForgeDirection;Lnet/minecraftforge/fluids/FluidStack;Z)I
    ALOAD 0
    INVOKEINTERFACE TFluidHandler$$7.TFluidHandler$$7$$impl ()Lnet/minecraftforge/fluids/IFluidHandler;
    ALOAD 1
    ALOAD 2
    ILOAD 3
    INVOKEINTERFACE net/minecraftforge/fluids/IFluidHandler.fill (Lnet/minecraftforge/common/util/ForgeDirection;Lnet/minecraftforge/fluids/FluidStack;Z)I
    IRETURN
    MAXSTACK = 4
    MAXLOCALS = 4

  // access flags 0x9
  public static drain(LTFluidHandler$$7;Lnet/minecraftforge/common/util/ForgeDirection;IZ)Lnet/minecraftforge/fluids/FluidStack;
    ALOAD 0
    INVOKEINTERFACE TFluidHandler$$7.TFluidHandler$$7$$impl ()Lnet/minecraftforge/fluids/IFluidHandler;
    ALOAD 1
    ILOAD 2
    ILOAD 3
    INVOKEINTERFACE net/minecraftforge/fluids/IFluidHandler.drain (Lnet/minecraftforge/common/util/ForgeDirection;IZ)Lnet/minecraftforge/fluids/FluidStack;
    ARETURN
    MAXSTACK = 4
    MAXLOCALS = 4

  // access flags 0x9
  public static canFill(LTFluidHandler$$7;Lnet/minecraftforge/common/util/ForgeDirection;Lnet/minecraftforge/fluids/Fluid;)Z
    ALOAD 0
    INVOKEINTERFACE TFluidHandler$$7.TFluidHandler$$7$$impl ()Lnet/minecraftforge/fluids/IFluidHandler;
    ALOAD 1
    ALOAD 2
    INVOKEINTERFACE net/minecraftforge/fluids/IFluidHandler.canFill (Lnet/minecraftforge/common/util/ForgeDirection;Lnet/minecraftforge/fluids/Fluid;)Z
    IRETURN
    MAXSTACK = 3
    MAXLOCALS = 3

  // access flags 0x9
  public static canDrain(LTFluidHandler$$7;Lnet/minecraftforge/common/util/ForgeDirection;Lnet/minecraftforge/fluids/Fluid;)Z
    ALOAD 0
    INVOKEINTERFACE TFluidHandler$$7.TFluidHandler$$7$$impl ()Lnet/minecraftforge/fluids/IFluidHandler;
    ALOAD 1
    ALOAD 2
    INVOKEINTERFACE net/minecraftforge/fluids/IFluidHandler.canDrain (Lnet/minecraftforge/common/util/ForgeDirection;Lnet/minecraftforge/fluids/Fluid;)Z
    IRETURN
    MAXSTACK = 3
    MAXLOCALS = 3

  // access flags 0x9
  public static copyFrom(LTFluidHandler$$7;Lcodechicken/multipart/TileMultipart;)V
    ALOAD 0
    ALOAD 1
    INVOKEINTERFACE TFluidHandler$$7.TFluidHandler$$7$$super$copyFrom (Lcodechicken/multipart/TileMultipart;)V
    ALOAD 1
    INSTANCEOF TFluidHandler$$7
    IFEQ L0
    ALOAD 0
    ALOAD 1
    INVOKEINTERFACE TFluidHandler$$7.TFluidHandler$$7$$impl ()Lnet/minecraftforge/fluids/IFluidHandler;
    INVOKEINTERFACE TFluidHandler$$7.TFluidHandler$$7$$impl_$eq (Lnet/minecraftforge/fluids/IFluidHandler;)V
   L0
    RETURN
    MAXSTACK = 2
    MAXLOCALS = 2
}
