// class version 50.0 (50)
// access flags 0x401
public abstract class TPowerReceptor$$2$class {


  // access flags 0x9
  public static $init$(LTPowerReceptor$$2;)V
    RETURN
    MAXSTACK = 1
    MAXLOCALS = 1

  // access flags 0x9
  public static bindPart(LTPowerReceptor$$2;Lcodechicken/multipart/TMultiPart;)V
    ALOAD 0
    ALOAD 1
    INVOKEINTERFACE TPowerReceptor$$2.TPowerReceptor$$2$$super$bindPart (Lcodechicken/multipart/TMultiPart;)V
    ALOAD 1
    INSTANCEOF buildcraft/api/power/IPowerReceptor
    IFEQ L0
    ALOAD 0
    ALOAD 1
    CHECKCAST buildcraft/api/power/IPowerReceptor
    INVOKEINTERFACE TPowerReceptor$$2.TPowerReceptor$$2$$impl_$eq (Lbuildcraft/api/power/IPowerReceptor;)V
   L0
   FRAME FULL [TPowerReceptor$$2 codechicken/multipart/TMultiPart] []
    RETURN
    MAXSTACK = 2
    MAXLOCALS = 2

  // access flags 0x9
  public static partRemoved(LTPowerReceptor$$2;Lcodechicken/multipart/TMultiPart;I)V
    ALOAD 0
    ALOAD 1
    ILOAD 2
    INVOKEINTERFACE TPowerReceptor$$2.TPowerReceptor$$2$$super$partRemoved (Lcodechicken/multipart/TMultiPart;I)V
    ALOAD 1
    ALOAD 0
    INVOKEINTERFACE TPowerReceptor$$2.TPowerReceptor$$2$$impl ()Lbuildcraft/api/power/IPowerReceptor;
    IF_ACMPNE L0
    ALOAD 0
    ACONST_NULL
    INVOKEINTERFACE TPowerReceptor$$2.TPowerReceptor$$2$$impl_$eq (Lbuildcraft/api/power/IPowerReceptor;)V
   L0
   FRAME FULL [TPowerReceptor$$2 codechicken/multipart/TMultiPart I] []
    RETURN
    MAXSTACK = 3
    MAXLOCALS = 3

  // access flags 0x9
  public static canAddPart(LTPowerReceptor$$2;Lcodechicken/multipart/TMultiPart;)Z
    ALOAD 0
    INVOKEINTERFACE TPowerReceptor$$2.TPowerReceptor$$2$$impl ()Lbuildcraft/api/power/IPowerReceptor;
    IFNULL L0
    ALOAD 1
    INSTANCEOF buildcraft/api/power/IPowerReceptor
    IFEQ L0
    ICONST_0
    IRETURN
   L0
   FRAME FULL [TPowerReceptor$$2 codechicken/multipart/TMultiPart] []
    ALOAD 0
    ALOAD 1
    INVOKEINTERFACE TPowerReceptor$$2.TPowerReceptor$$2$$super$canAddPart (Lcodechicken/multipart/TMultiPart;)Z
    IRETURN
    MAXSTACK = 2
    MAXLOCALS = 2

  // access flags 0x9
  public static getPowerReceiver(LTPowerReceptor$$2;Lnet/minecraftforge/common/util/ForgeDirection;)Lbuildcraft/api/power/PowerHandler$PowerReceiver;
    ALOAD 0
    INVOKEINTERFACE TPowerReceptor$$2.TPowerReceptor$$2$$impl ()Lbuildcraft/api/power/IPowerReceptor;
    ALOAD 1
    INVOKEINTERFACE buildcraft/api/power/IPowerReceptor.getPowerReceiver (Lnet/minecraftforge/common/util/ForgeDirection;)Lbuildcraft/api/power/PowerHandler$PowerReceiver;
    ARETURN
    MAXSTACK = 2
    MAXLOCALS = 2

  // access flags 0x9
  public static doWork(LTPowerReceptor$$2;Lbuildcraft/api/power/PowerHandler;)V
    ALOAD 0
    INVOKEINTERFACE TPowerReceptor$$2.TPowerReceptor$$2$$impl ()Lbuildcraft/api/power/IPowerReceptor;
    ALOAD 1
    INVOKEINTERFACE buildcraft/api/power/IPowerReceptor.doWork (Lbuildcraft/api/power/PowerHandler;)V
    RETURN
    MAXSTACK = 2
    MAXLOCALS = 2

  // access flags 0x9
  public static getWorld(LTPowerReceptor$$2;)Lnet/minecraft/world/World;
    ALOAD 0
    INVOKEINTERFACE TPowerReceptor$$2.TPowerReceptor$$2$$impl ()Lbuildcraft/api/power/IPowerReceptor;
    INVOKEINTERFACE buildcraft/api/power/IPowerReceptor.getWorld ()Lnet/minecraft/world/World;
    ARETURN
    MAXSTACK = 1
    MAXLOCALS = 1

  // access flags 0x9
  public static copyFrom(LTPowerReceptor$$2;Lcodechicken/multipart/TileMultipart;)V
    ALOAD 0
    ALOAD 1
    INVOKEINTERFACE TPowerReceptor$$2.TPowerReceptor$$2$$super$copyFrom (Lcodechicken/multipart/TileMultipart;)V
    ALOAD 1
    INSTANCEOF TPowerReceptor$$2
    IFEQ L0
    ALOAD 0
    ALOAD 1
    INVOKEINTERFACE TPowerReceptor$$2.TPowerReceptor$$2$$impl ()Lbuildcraft/api/power/IPowerReceptor;
    INVOKEINTERFACE TPowerReceptor$$2.TPowerReceptor$$2$$impl_$eq (Lbuildcraft/api/power/IPowerReceptor;)V
   L0
    RETURN
    MAXSTACK = 2
    MAXLOCALS = 2
}
