// class version 50.0 (50)
// access flags 0x401
public abstract class TPowerEmitter$$4$class {


  // access flags 0x9
  public static $init$(LTPowerEmitter$$4;)V
    RETURN
    MAXSTACK = 1
    MAXLOCALS = 1

  // access flags 0x9
  public static bindPart(LTPowerEmitter$$4;Lcodechicken/multipart/TMultiPart;)V
    ALOAD 0
    ALOAD 1
    INVOKEINTERFACE TPowerEmitter$$4.TPowerEmitter$$4$$super$bindPart (Lcodechicken/multipart/TMultiPart;)V
    ALOAD 1
    INSTANCEOF buildcraft/api/power/IPowerEmitter
    IFEQ L0
    ALOAD 0
    ALOAD 1
    CHECKCAST buildcraft/api/power/IPowerEmitter
    INVOKEINTERFACE TPowerEmitter$$4.TPowerEmitter$$4$$impl_$eq (Lbuildcraft/api/power/IPowerEmitter;)V
   L0
   FRAME FULL [TPowerEmitter$$4 codechicken/multipart/TMultiPart] []
    RETURN
    MAXSTACK = 2
    MAXLOCALS = 2

  // access flags 0x9
  public static partRemoved(LTPowerEmitter$$4;Lcodechicken/multipart/TMultiPart;I)V
    ALOAD 0
    ALOAD 1
    ILOAD 2
    INVOKEINTERFACE TPowerEmitter$$4.TPowerEmitter$$4$$super$partRemoved (Lcodechicken/multipart/TMultiPart;I)V
    ALOAD 1
    ALOAD 0
    INVOKEINTERFACE TPowerEmitter$$4.TPowerEmitter$$4$$impl ()Lbuildcraft/api/power/IPowerEmitter;
    IF_ACMPNE L0
    ALOAD 0
    ACONST_NULL
    INVOKEINTERFACE TPowerEmitter$$4.TPowerEmitter$$4$$impl_$eq (Lbuildcraft/api/power/IPowerEmitter;)V
   L0
   FRAME FULL [TPowerEmitter$$4 codechicken/multipart/TMultiPart I] []
    RETURN
    MAXSTACK = 3
    MAXLOCALS = 3

  // access flags 0x9
  public static canAddPart(LTPowerEmitter$$4;Lcodechicken/multipart/TMultiPart;)Z
    ALOAD 0
    INVOKEINTERFACE TPowerEmitter$$4.TPowerEmitter$$4$$impl ()Lbuildcraft/api/power/IPowerEmitter;
    IFNULL L0
    ALOAD 1
    INSTANCEOF buildcraft/api/power/IPowerEmitter
    IFEQ L0
    ICONST_0
    IRETURN
   L0
   FRAME FULL [TPowerEmitter$$4 codechicken/multipart/TMultiPart] []
    ALOAD 0
    ALOAD 1
    INVOKEINTERFACE TPowerEmitter$$4.TPowerEmitter$$4$$super$canAddPart (Lcodechicken/multipart/TMultiPart;)Z
    IRETURN
    MAXSTACK = 2
    MAXLOCALS = 2

  // access flags 0x9
  public static canEmitPowerFrom(LTPowerEmitter$$4;Lnet/minecraftforge/common/util/ForgeDirection;)Z
    ALOAD 0
    INVOKEINTERFACE TPowerEmitter$$4.TPowerEmitter$$4$$impl ()Lbuildcraft/api/power/IPowerEmitter;
    ALOAD 1
    INVOKEINTERFACE buildcraft/api/power/IPowerEmitter.canEmitPowerFrom (Lnet/minecraftforge/common/util/ForgeDirection;)Z
    IRETURN
    MAXSTACK = 2
    MAXLOCALS = 2

  // access flags 0x9
  public static copyFrom(LTPowerEmitter$$4;Lcodechicken/multipart/TileMultipart;)V
    ALOAD 0
    ALOAD 1
    INVOKEINTERFACE TPowerEmitter$$4.TPowerEmitter$$4$$super$copyFrom (Lcodechicken/multipart/TileMultipart;)V
    ALOAD 1
    INSTANCEOF TPowerEmitter$$4
    IFEQ L0
    ALOAD 0
    ALOAD 1
    INVOKEINTERFACE TPowerEmitter$$4.TPowerEmitter$$4$$impl ()Lbuildcraft/api/power/IPowerEmitter;
    INVOKEINTERFACE TPowerEmitter$$4.TPowerEmitter$$4$$impl_$eq (Lbuildcraft/api/power/IPowerEmitter;)V
   L0
    RETURN
    MAXSTACK = 2
    MAXLOCALS = 2
}
